watch_webcam/__init__.py
watch_webcam/cli.py
watch_webcam/video.py
watch_webcam/actions/__init__.py
watch_webcam/actions/base.py
watch_webcam/actions/light.py
watch_webcam/actions/media.py
watch_webcam/actions/xscreensaver.py
watch_webcam-0.0.2.dist-info/LICENSE
watch_webcam-0.0.2.dist-info/METADATA
watch_webcam-0.0.2.dist-info/WHEEL
watch_webcam-0.0.2.dist-info/entry_points.txt
watch_webcam-0.0.2.dist-info/top_level.txt
watch_webcam-0.0.2.dist-info/RECORD
