Metadata-Version: 2.2
Name: watch_webcam
Version: 0.0.2
Summary: A small script to watch your webcam and do actions
Author-email: Christof Damian <christof@damian.net>
License:                     GNU GENERAL PUBLIC LICENSE
Project-URL: Homepage, https://github.com/christofdamian/watch-webcam
Project-URL: Issues, https://github.com/christofdamian/watch-webcam/issues
Classifier: Programming Language :: Python :: 3
Classifier: Operating System :: POSIX :: Linux
Classifier: License :: OSI Approved :: GNU General Public License v3 (GPLv3)
Requires-Python: >=3.8
License-File: LICENSE
Requires-Dist: leglight
Requires-Dist: pyyaml
